{
  "user": [{
      "email": "w@w.com",
      "img": "https://www.photoframemaster.com/res/templates/thumb_small/bright-blue-kaleidoscope.png",
      "pass": "w",
      "username": "Wixer"
    },
    {
      "email": "cp@cp.com",
      "img": "http://www.advertguru.co.zw/wp-content/uploads/2015/09/logo-designing-in-Harare-Zimbabwe.jpg",
      "pass": "cp",
      "username": "Check Boing"
    },
    {
      "email": "g@g.com",
      "img": "https://i.pinimg.com/originals/ee/8e/1c/ee8e1ce91c0ffddf0105b4173f597db8.jpg",
      "pass": "g",
      "username": "Googloo"
    },
    {
      "email": "m@m.com",
      "username": "Microsolve",
      "img": "https://www.designfreelogoonline.com/wp-content/uploads/2014/12/00240-Design-Free-3D-Company-Logo-Templates-03.png",
      "pass": "m"
    },
    {
      "email": "d@d.com",
      "skills": [
        "Frontend Developer",
        "Fullstack Developer",
        "Web Developer"
      ],
      "archivedJobsIds": [],
      "savedJobsIds": [],
      "appliedJobsIds": [],
      "img": "https://www.afrombira.com/img/no-user.png",
      "pass": "d",
      "username": "Dalia"
    }
  ],
  "job": [{
      "title": "Account Manager",
      "owner": {
        "img": "https://www.photoframemaster.com/res/templates/thumb_small/bright-blue-kaleidoscope.png",
        "username": "Wixer"
      },
      "createdAt": 1575206189973,
      "address": "Tel Aviv",
      "perks": [
        "parking",
        "mug-hot"
      ],
      "posts": [{
          "_id": "124",
          "from": "Anonymous",
          "createdAt": 1575206189983,
          "txt": "Lorem ipsum dolor sit, amet consectetur adipisicing elit. Sunt, iure atque maxime harum exercitationem sapiente! Vero maxime ex exercitationem impedit. Quaerat",
          "likes": 2
        },
        {
          "_id": "1239",
          "from": "Anonymous",
          "createdAt": 1575206189981,
          "txt": "Lorem ipsum dolor sit, amet consectetur adipisicing elit. Sunt, iure atque maxime harum exercitationem sapiente! Vero maxime ex exercitationem impedit. Quaerat",
          "likes": 0
        }
      ],
      "reqSkills": ["Frontend Developer", "Web Developer", "Designer"],
      "payment": 8900,
      "desc": "Develops new business by analyzing account potential; initiating, developing, and closing sales; recommending new applications and sales strategies.\nIdentifies potential in accounts by studying current business; interviewing key customer personnel and company personnel who have worked with customer; identifying and evaluating additional needs; analyzing opportunities.",
      "img": "https://images.unsplash.com/photo-1531973576160-7125cd663d86?ixlib=rb-1.2.1&ixid=eyJhcHBfaWQiOjEyMDd9&auto=format&fit=crop&w=1050&q=80"
    },
    {
      "title": "Project Manager",
      "owner": {
        "img": "https://i.pinimg.com/originals/ee/8e/1c/ee8e1ce91c0ffddf0105b4173f597db8.jpg",
        "username": "Googloo"
      },
      "createdAt": 1575206189975,
        "address": "Raanana",
      "perks": [
        "paw"
      ],
      "posts": [{
          "_id": "koep",
          "from": "Anonymous",
          "createdAt": 1575206189983,
          "txt": "Lorem ipsum dolor sit, amet consectetur adipisicing elit. Sunt, iure atque maxime harum exercitationem sapiente! Vero maxime ex exercitationem impedit. Quaerat",
          "likes": 1
        },
        {
          "_id": "2io3",
          "from": "Anonymous",
          "createdAt": 1575206189981,
          "txt": "Lorem ipsum dolor sit, amet consectetur adipisicing elit. Sunt, iure atque maxime harum exercitationem sapiente! Vero maxime ex exercitationem impedit. Quaerat",
          "likes": 0
        }
      ],
      "reqSkills": ["Frontend Developer", "Web Developer", "Designer"],
      "saves": 5,
      "applicants": [],
      "payment": 8900,
      "desc": "Builds market position by locating, developing, defining, and closing business relationships.\nIdentifies trendsetter ideas by researching industry and related events, publications, and announcements.\nTracks individual contributors and their accomplishments.\nLocates or proposes potential business deals by contacting potential partners.\nDiscovers and explores business opportunities.",
      "img": "https://images.unsplash.com/photo-1454165804606-c3d57bc86b40?ixlib=rb-1.2.1&ixid=eyJhcHBfaWQiOjEyMDd9&auto=format&fit=crop&w=1050&q=80"
    },
    {
      "title": "Backend Developer",
      "owner": {
        "img": "http://www.advertguru.co.zw/wp-content/uploads/2015/09/logo-designing-in-Harare-Zimbabwe.jpg",
        "username": "Check Boing"
      },
      "createdAt": 1575206189961,
        "address": "Bat Yam",
      "perks": [
        "utensils",
        "paw"
      ],
      "posts": [{
          "_id": "9823u",
          "from": "Anonymous",
          "createdAt": 1575206189983,
          "txt": "Lorem ipsum dolor sit, amet consectetur adipisicing elit. Sunt, iure atque maxime harum exercitationem sapiente! Vero maxime ex exercitationem impedit. Quaerat",
          "likes": 4
        },
        {
          "_id": "dawlk",
          "from": "Anonymous",
          "createdAt": 1575206189981,
          "txt": "Lorem ipsum dolor sit, amet consectetur adipisicing elit. Sunt, iure atque maxime harum exercitationem sapiente! Vero maxime ex exercitationem impedit. Quaerat",
          "likes": 0
        }
      ],
      "reqSkills": ["Frontend Developer", "Web Developer", "Designer"],
      "payment": 8900,
      "desc": "Recommends equity investments.\nDevelops negotiating strategies and positions by studying integration of new venture with company strategies and operations.\nExamines risks and potentials for the business opportunities.\nEstimates partners’ needs and goals.",
      "img": "https://images.unsplash.com/photo-1519389950473-47ba0277781c?ixlib=rb-1.2.1&ixid=eyJhcHBfaWQiOjEyMDd9&auto=format&fit=crop&w=1050&q=80"
    },
    {
      "title": "Account Manager",
      "owner": {
        "username": "Microsolve",
        "img": "https://www.designfreelogoonline.com/wp-content/uploads/2014/12/00240-Design-Free-3D-Company-Logo-Templates-03.png"
      },
      "createdAt": 1575206189967,
        "address": "Eilat",
      "perks": [],
      "posts": [{
          "_id": "ijel3",
          "from": "Anonymous",
          "createdAt": 1575206189983,
          "txt": "Lorem ipsum dolor sit, amet consectetur adipisicing elit. Sunt, iure atque maxime harum exercitationem sapiente! Vero maxime ex exercitationem impedit. Quaerat",
          "likes": 3
        },
        {
          "_id": "diow8",
          "from": "Anonymous",
          "createdAt": 1575206189981,
          "txt": "Lorem ipsum dolor sit, amet consectetur adipisicing elit. Sunt, iure atque maxime harum exercitationem sapiente! Vero maxime ex exercitationem impedit. Quaerat",
          "likes": 0
        }
      ],
      "reqSkills": ["Frontend Developer", "Web Developer", "Designer"],
      "payment": 8900,
      "desc": "Closes new business deals by coordinating requirements; developing and negotiating contracts; and integrating contract requirements with business operations.\nProtects organization’s value by keeping information confidential.\nEnhances organization’s reputation by accepting ownership for accomplishing new and different requests.",
      "img": "https://images.unsplash.com/photo-1497366811353-6870744d04b2?ixlib=rb-1.2.1&ixid=eyJhcHBfaWQiOjEyMDd9&auto=format&fit=crop&w=750&q=80"
    },
    {
      "title": "Product Manager",
      "owner": {
        "username": "Googloo",
        "img": "https://i.pinimg.com/originals/ee/8e/1c/ee8e1ce91c0ffddf0105b4173f597db8.jpg"
      },
      "createdAt": 1575206189959,
        "address": "Ashdod",
      "perks": [
        "paw"
      ],
      "posts": [{
          "_id": "rw3f",
          "from": "Anonymous",
          "createdAt": 1575206189983,
          "txt": "Lorem ipsum dolor sit, amet consectetur adipisicing elit. Sunt, iure atque maxime harum exercitationem sapiente! Vero maxime ex exercitationem impedit. Quaerat",
          "likes": 2
        },
        {
          "_id": "esfk3s",
          "from": "Anonymous",
          "createdAt": 1575206189981,
          "txt": "Lorem ipsum dolor sit, amet consectetur adipisicing elit. Sunt, iure atque maxime harum exercitationem sapiente! Vero maxime ex exercitationem impedit. Quaerat",
          "likes": 0
        }
      ],
      "reqSkills": ["Frontend Developer", "Web Developer", "Designer"],
      "saves": 6,
      "applicants": [],
      "payment": 8900,
      "desc": "Builds market position by locating, developing, defining, and closing business relationships.\nIdentifies trendsetter ideas by researching industry and related events, publications, and announcements.\nTracks individual contributors and their accomplishments.\nLocates or proposes potential business deals by contacting potential partners.\nDiscovers and explores business opportunities.",
      "img": "https://images.unsplash.com/photo-1557804506-669a67965ba0?ixlib=rb-1.2.1&ixid=eyJhcHBfaWQiOjEyMDd9&auto=format&fit=crop&w=667&q=80"
    }
  ]
}